MANIFEST.in
README.md
setup.py
hacktoberfest_jems/__init__.py
hacktoberfest_jems/main.py
hacktoberfest_jems.egg-info/PKG-INFO
hacktoberfest_jems.egg-info/SOURCES.txt
hacktoberfest_jems.egg-info/dependency_links.txt
hacktoberfest_jems.egg-info/entry_points.txt
hacktoberfest_jems.egg-info/top_level.txt
hacktoberfest_jems/data/contributors.json