Metadata-Version: 1.0
Name: hacktoberfest-jems
Version: 1.0.2
Summary: An application to celebrate hacktoberfest!
Home-page: UNKNOWN
Author: Tiffany Souterre
Author-email: UNKNOWN
License: UNKNOWN
Platform: UNKNOWN
